[
  {
    "id": 1,
    "body": "X と Y が 0 または 1 をとるとき、演算 □ の真理値表を求める問題。次の 4 つの候補のうち、X □ Y の真理値表が問題文の条件（X AND (X□Y)、X OR (X□Y) の値）を満たすものはどれか？",
    "choices": [
      {
        "text": "ア: (0□0)=0, (0□1)=0, (1□0)=0, (1□1)=1",
        "explanation": "不正解。X□Y を AND とした場合であり、X OR (X□Y) が (0,0) で 1 にならず条件を満たさない。"
      },
      {
        "text": "イ: (0□0)=0, (0□1)=1, (1□0)=0, (1□1)=1",
        "explanation": "不正解。0□0 が 0 なので X OR (X□Y) が (0,0) のとき 1 にならず条件と矛盾する。"
      },
      {
        "text": "ウ: (0□0)=1, (0□1)=1, (1□0)=0, (1□1)=1",
        "explanation": "正解。0 行 0 列で OR が 1、1 行 0 列で AND が 0 になるなど、すべての条件を満たす。"
      },
      {
        "text": "エ: (0□0)=1, (0□1)=1, (1□0)=1, (1□1)=0",
        "explanation": "不正解。(1□1)=0 のため X AND (X□Y) が (1,1) で 0 となり条件を満たさない。"
      }
    ],
    "correctChoiceIndex": 2
  },
  {
    "id": 2,
    "body": "a〜z の ASCII コードの 1 の位をハッシュ値としてサイズ 10 のハッシュ表に格納するとき、衝突が起こるキーの組み合わせはどれか？",
    "choices": [
      {
        "text": "ア: a と i",
        "explanation": "ASCII 97 と 105 で 1 の位は 7 と 5。衝突しない。"
      },
      {
        "text": "イ: b と r",
        "explanation": "ASCII 98 と 114 で 8 と 4。衝突しない。"
      },
      {
        "text": "ウ: c と l",
        "explanation": "ASCII 99 と 108 で 9 と 8。衝突しない。"
      },
      {
        "text": "エ: d と x",
        "explanation": "正解。ASCII 100 と 120 ともに 1 の位は 0 で同じスロットに格納される。"
      }
    ],
    "correctChoiceIndex": 3
  },
  {
    "id": 3,
    "body": "CPU X と CPU Y の平均メモリアクセス時間が等しくなるとき、キャッシュヒット率はいくらか？（X: キャッシュ40ns 主記憶400ns, Y: 20ns, 580ns）",
    "choices": [
      {
        "text": "ア: 0.75",
        "explanation": "ヒット率 0.75 では X の平均は 400−360×0.75=130ns、Y は 580−560×0.75=160ns で一致しない。"
      },
      {
        "text": "イ: 0.90",
        "explanation": "正解。h=0.9 とすると両者とも 400−360×0.9=76ns, 580−560×0.9=76ns で等しくなる。"
      },
      {
        "text": "ウ: 0.95",
        "explanation": "h=0.95 では 400−342=58ns と 580−532=48ns で差がある。"
      },
      {
        "text": "エ: 0.96",
        "explanation": "h=0.96 では 400−345.6=54.4ns と 580−537.6=42.4ns で一致しない。"
      }
    ],
    "correctChoiceIndex": 1
  },
  {
    "id": 4,
    "body": "MTBF=3,000h, MTTR=1,000h のシステムが翌年度に MTBF を 20% 改善し、MTTR を 10% 改善したときの稼働率（Availability）は？",
    "choices": [
      {
        "text": "ア: 69%",
        "explanation": "計算誤り。"
      },
      {
        "text": "イ: 73%",
        "explanation": "計算誤り。"
      },
      {
        "text": "ウ: 77%",
        "explanation": "計算誤り。"
      },
      {
        "text": "エ: 80%",
        "explanation": "正解。稼働率 = 3,600 / (3,600 + 900) = 0.8 → 80%。"
      }
    ],
    "correctChoiceIndex": 3
  },
  {
    "id": 5,
    "body": "複数 Web サービスの入出力を連結して新たなサービスを提供する “ロジックマッシュアップ” の例はどれか？",
    "choices": [
      {
        "text": "ア: 飲食店ページに地図コンテンツを組み合わせて表示する",
        "explanation": "UI マッシュアップの例であり、入出力の連結はない。"
      },
      {
        "text": "イ: 投資商品データと経済指標データを取得しグラフ化する",
        "explanation": "複数サービスのデータを同時に表示するだけで連結処理がない。"
      },
      {
        "text": "ウ: 宿泊施設リストを取得し、その結果を利用して空室情報を取得・統合する",
        "explanation": "正解。一つのサービスの出力を次のサービスの入力に用いる連結型処理である。"
      },
      {
        "text": "エ: Ajax で地図を部分更新表示する",
        "explanation": "単一サービス内の表示技法でありマッシュアップとは異なる。"
      }
    ],
    "correctChoiceIndex": 2
  },
  {
    "id": 6,
    "body": "液晶ディスプレイなどで傾いた直線のジャギーを滑らかに表示する手法はどれか？",
    "choices": [
      {
        "text": "ア: アンチエイリアシング",
        "explanation": "正解。サンプリング誤差によるギザギザを平均化して滑らかにする技術。"
      },
      {
        "text": "イ: シェーディング",
        "explanation": "陰影計算法で曲面の明るさを計算する手法。"
      },
      {
        "text": "ウ: テクスチャマッピング",
        "explanation": "画像をポリゴン表面に貼り付ける手法。"
      },
      {
        "text": "エ: バンプマッピング",
        "explanation": "凹凸感を表現する法線擬似処理で滑らか化とは別。"
      }
    ],
    "correctChoiceIndex": 0
  },
  {
    "id": 7,
    "body": "DBMS におけるトランザクション性質の一つ“原子性（Atomicity）”の説明はどれか？",
    "choices": [
      {
        "text": "ア: 同一処理は何度実行しても結果が同じ（冪等性）",
        "explanation": "これは“再実行可能性”であり原子性ではない。"
      },
      {
        "text": "イ: 障害後も更新が保証される（耐久性）",
        "explanation": "耐久性に関する説明。"
      },
      {
        "text": "ウ: すべての処理が実行されるか取り消されるかのどちらかである",
        "explanation": "正解。これが原子性。"
      },
      {
        "text": "エ: 他トランザクションの影響を受けない（独立性）",
        "explanation": "分離性に関する説明。"
      }
    ],
    "correctChoiceIndex": 2
  },
  {
    "id": 8,
    "body": "LAN 間接続装置に関する記述のうち適切なものはどれか？",
    "choices": [
      {
        "text": "ア: ゲートウェイは OSI 第 1〜3 層だけを変換する",
        "explanation": "ゲートウェイは第 7 層まで含むプロトコル変換を行う。"
      },
      {
        "text": "イ: ブリッジは IP アドレスでフレームを中継する",
        "explanation": "ブリッジは MAC アドレスを用いる。"
      },
      {
        "text": "ウ: リピータは同種セグメント間で信号を再生し伝送距離を延長する",
        "explanation": "正解。"
      },
      {
        "text": "エ: ルータは MAC アドレスを用いてフレームを中継する",
        "explanation": "ルータは IP アドレスを用いてパケットを中継する。"
      }
    ],
    "correctChoiceIndex": 2
  },
  {
    "id": 9,
    "body": "ペネトレーションテストに該当するものはどれか？",
    "choices": [
      {
        "text": "ア: 仕様書・ソースをレビューしてセキュリティ問題を検査する",
        "explanation": "これはセキュリティ設計レビュー。"
      },
      {
        "text": "イ: 公開 Web サーバのファイル改ざんをハッシュで検知する",
        "explanation": "ファイルインテグリティ監視でありペネトレーションではない。"
      },
      {
        "text": "ウ: 公開 Web サーバやネットワークに実際に侵入できるか確認する",
        "explanation": "正解。実際に攻撃を試みるテストがペネトレーションテスト。"
      },
      {
        "text": "エ: IPFIX から異常通信を監視する",
        "explanation": "ネットワーク監視による検知型のセキュリティ監査。"
      }
    ],
    "correctChoiceIndex": 2
  },
  {
    "id": 10,
    "body": "SQL インジェクション対策として有効なものはどれか？",
    "choices": [
      {
        "text": "ア: http/https で始まる URL だけを Web ページに出力許可する",
        "explanation": "XSS 対策の一例であり SQLi には直接効果がない。"
      },
      {
        "text": "イ: 外部パラメータでファイル名を直接指定しない",
        "explanation": "ディレクトリトラバーサル対策に近い。"
      },
      {
        "text": "ウ: 外部サイトからのスタイルシート取り込みを禁止する",
        "explanation": "XSS や clickjacking 対策の一例。"
      },
      {
        "text": "エ: プレースホルダ（バインド変数）を使ってクエリを組み立てる",
        "explanation": "正解。パラメータを値として分離し SQL 文として扱わない。"
      }
    ],
    "correctChoiceIndex": 3
  },
  {
    "id": 11,
    "body": "上位モジュールから行う結合テスト（トップダウンテスト）で，下位モジュールの代替として使用するテスト用モジュールはどれか？",
    "choices": [
      {
        "text": "ア: エミュレータ",
        "explanation": "ハードウェア動作を模倣するソフトウェアであり対象外。"
      },
      {
        "text": "イ: シミュレータ",
        "explanation": "同様に動作を模倣するがモジュール代替とは異なる。"
      },
      {
        "text": "ウ: スタブ",
        "explanation": "正解。呼び出される下位モジュールを仮実装したダミー部品。"
      },
      {
        "text": "エ: ドライバ",
        "explanation": "下位から上位を呼び出すボトムアップテストで使う部品。"
      }
    ],
    "correctChoiceIndex": 2
  },
  {
    "id": 12,
    "body": "スクラム開発で毎日同じ時間と場所で進捗を共有するイベントはどれか？",
    "choices": [
      {
        "text": "ア: スプリントプランニング",
        "explanation": "スプリント開始時に作業を計画する会議。"
      },
      {
        "text": "イ: スプリントレトロスペクティブ",
        "explanation": "スプリント後に振り返りを行う会議。"
      },
      {
        "text": "ウ: スプリントレビュー",
        "explanation": "成果物をレビューしステークホルダーに示す会議。"
      },
      {
        "text": "エ: デイリースクラム",
        "explanation": "正解。開発チームが進捗と課題を共有する毎日の短い会議。"
      }
    ],
    "correctChoiceIndex": 3
  },
  {
    "id": 13,
    "body": "アローダイアグラムで表されるプロジェクトの最短完了日数は？",
    "choices": [
      {
        "text": "ア: 105 日",
        "explanation": "クリティカルパスを計算すると不足。"
      },
      {
        "text": "イ: 115 日",
        "explanation": "クリティカルパスと一致しない。"
      },
      {
        "text": "ウ: 120 日",
        "explanation": "正解。最長経路の合計所要時間。"
      },
      {
        "text": "エ: 125 日",
        "explanation": "余裕時間を無視して長すぎる。"
      }
    ],
    "correctChoiceIndex": 2
  },
  {
    "id": 14,
    "body": "開発部門と運用部門が分かれている組織で、新規サービス移行を円滑に進める方法はどれか？",
    "choices": [
      {
        "text": "ア: 運用テスト後、開発が仕様と運用方法を運用部門に説明する",
        "explanation": "運用部門の要件が開発前に反映されない。"
      },
      {
        "text": "イ: 運用テストは運用部門のみで実施する",
        "explanation": "開発部門の支援がなく情報共有が不足する。"
      },
      {
        "text": "ウ: 運用部門も運用要件の抽出に積極的に参加する",
        "explanation": "正解。開発の上流工程から運用部門が参加し要件を共有することで移行が円滑になる。"
      },
      {
        "text": "エ: 開発部門が運用マニュアルを作成し運用部門に引き渡す",
        "explanation": "ウォーターフォール的な一方通行で移行リスクが残る。"
      }
    ],
    "correctChoiceIndex": 2
  },
  {
    "id": 15,
    "body": "ビッグデータ分析前段階で非構造化データを構造化データへ加工する処理の例はどれか？",
    "choices": [
      {
        "text": "ア: RDB から CSV に抽出する",
        "explanation": "既に構造化されたデータ同士の変換。"
      },
      {
        "text": "イ: 個人情報を匿名化する",
        "explanation": "匿名化はプライバシー保護であり構造化化ではない。"
      },
      {
        "text": "ウ: 住所表記を正規化する",
        "explanation": "半構造データの正規化だが非構造→構造とは言いにくい。"
      },
      {
        "text": "エ: ソーシャルメディアの口コミを単語分解し要約を作成し DB に格納する",
        "explanation": "正解。テキストという非構造データを NLP 処理して構造化し格納する例。"
      }
    ],
    "correctChoiceIndex": 3
  },
  {
    "id": 16,
    "body": "コアコンピタンスを説明したものはどれか？",
    "choices": [
      {
        "text": "ア: 基本精神や行動指針（ミッション・ビジョン）",
        "explanation": "企業理念の説明。"
      },
      {
        "text": "イ: 事業戦略で達成すべき目標（ゴール）",
        "explanation": "経営目標でありコアコンピタンスではない。"
      },
      {
        "text": "ウ: ビジネス環境の機会と脅威",
        "explanation": "SWOT の外部環境分析。"
      },
      {
        "text": "エ: 競争優位の源泉となる経営資源・企業能力",
        "explanation": "正解。"
      }
    ],
    "correctChoiceIndex": 3
  },
  {
    "id": 17,
    "body": "マーケティング戦略でいうブルーオーシャンはどのような市場を指すか？",
    "choices": [
      {
        "text": "ア: 競争が存在しない未開拓市場",
        "explanation": "正解。競争のない新しい需要を開拓する市場を指す。"
      },
      {
        "text": "イ: コモディティ化が進んだ既存市場",
        "explanation": "これは“レッドオーシャン”に近い。"
      },
      {
        "text": "ウ: アイディアをビジネスに育成する期間",
        "explanation": "製品化期間の説明。"
      },
      {
        "text": "エ: 市場化までの障壁",
        "explanation": "イノベーションの死の谷の説明。"
      }
    ],
    "correctChoiceIndex": 0
  },
  {
    "id": 18,
    "body": "HR テックの説明として適切なのはどれか？",
    "choices": [
      {
        "text": "ア: 住宅内のエネルギー管理を支援する IoT ソリューション",
        "explanation": "HEMS（Home Energy Management System）の例。"
      },
      {
        "text": "イ: 既存ビジネスを破壊する新興 ICT やビジネスモデル",
        "explanation": "ディスラプティブ・テクノロジの説明。"
      },
      {
        "text": "ウ: 個人資金情報統合や P2P レンディングなどの FinTech",
        "explanation": "金融領域のテック。"
      },
      {
        "text": "エ: 採用・育成・評価など人事業務に AI やビッグデータを活用するソリューション",
        "explanation": "正解。"
      }
    ],
    "correctChoiceIndex": 3
  },
  {
    "id": 19,
    "body": "要因 x と品質特性 y をプロットした散布図が右上がりの直線状であった。この図から読み取れることはどれか？",
    "choices": [
      {
        "text": "ア: 2 次回帰係数の計算が必要である",
        "explanation": "線形に近いため 1 次回帰で十分。"
      },
      {
        "text": "イ: y から x を推定する回帰式と同じ式になる",
        "explanation": "逆回帰式は一般に異なる。"
      },
      {
        "text": "ウ: x と y の相関係数は正である",
        "explanation": "正解。右上がりは正の相関を示す。"
      },
      {
        "text": "エ: x と y の相関係数は負である",
        "explanation": "右上がりでは負ではない。"
      }
    ],
    "correctChoiceIndex": 2
  },
  {
    "id": 20,
    "body": "日本において“産業財産権”と総称される 4 つの権利の組合せはどれか？",
    "choices": [
      {
        "text": "ア: 意匠権，実用新案権，商標権，特許権",
        "explanation": "正解。"
      },
      {
        "text": "イ: 意匠権，実用新案権，著作権，特許権",
        "explanation": "著作権は産業財産権ではなく著作権法で保護される。"
      },
      {
        "text": "ウ: 意匠権，商標権，著作権，特許権",
        "explanation": "実用新案権が欠けており著作権を含む。"
      },
      {
        "text": "エ: 実用新案権，商標権，著作権，特許権",
        "explanation": "意匠権が欠け著作権が含まれる。"
      }
    ],
    "correctChoiceIndex": 0
  },
  {
    "id": 21,
    "body": "関数 convDecimal で“0”と“1”だけから成る文字列を 2 進数として整数に変換するプログラムの空欄に入る式はどれか？",
    "choices": [
      {
        "text": "ア: result ＋ int(binary[length − i + 1])",
        "explanation": "左シフトが行われず桁重みを考慮しない。"
      },
      {
        "text": "イ: result ＋ int(binary[i])",
        "explanation": "左シフトがないため桁重みを考慮しない。"
      },
      {
        "text": "ウ: result × 2 ＋ int(binary[length − i + 1])",
        "explanation": "文字列を右から読めばよいが、ここでは左から読んでいるため不適切。"
      },
      {
        "text": "エ: result × 2 ＋ int(binary[i])",
        "explanation": "正解。左からビットを読み取り result を 2 倍し最下位ビットに現在の値を加えていく。"
      }
    ],
    "correctChoiceIndex": 3
  },
  {
    "id": 22,
    "body": "merge({2,3}, {1,4}) を呼び出したとき、while (j≦n2) 内の行 work[k] ← data2[j] が実行される回数は？",
    "choices": [
      {
        "text": "ア: 実行されない",
        "explanation": "data2 の 2 番目の要素 4 が残るため 1 回は実行される。"
      },
      {
        "text": "イ: 1 回実行される",
        "explanation": "正解。{1} が先に取り込まれ、新しい j=2 となり最後に 4 が 1 回コピーされる。"
      },
      {
        "text": "ウ: 2 回実行される",
        "explanation": "data2 の残要素は 1 つだけなので 2 回は実行されない。"
      },
      {
        "text": "エ: 3 回実行される",
        "explanation": "残要素が 1 つなので 3 回は実行されない。"
      }
    ],
    "correctChoiceIndex": 1
  },
  {
    "id": 23,
    "body": "16 進小数 0.C を 10 進小数に変換したものはどれか。",
    "choices": [
      {
        "text": "ア: 0.12",
        "explanation": "0.C は 12/16=0.75 なので 0.12 ではない。"
      },
      {
        "text": "イ: 0.55",
        "explanation": "0.C は 0.75 に等しいため誤り。"
      },
      {
        "text": "ウ: 0.75",
        "explanation": "正解。C(12) ÷ 16 = 0.75。"
      },
      {
        "text": "エ: 0.84",
        "explanation": "16 進 0.D(13) の場合の値に近い。"
      }
    ],
    "correctChoiceIndex": 2
  },
  {
    "id": 24,
    "body": "双方向リストに新たなノード G を A と K の間に挿入した後、変更が必要なポインタだけを列挙したものはどれか。",
    "choices": [
      {
        "text": "ア: a, b, e, f",
        "explanation": "挿入後も A の prev は 0、K の next は変わらないため b, e は不要。"
      },
      {
        "text": "イ: a, e, f",
        "explanation": "e( K の next ) は変更不要。"
      },
      {
        "text": "ウ: a, f",
        "explanation": "正解。A.next (a) と K.prev (f) だけを更新すればよい。"
      },
      {
        "text": "エ: b, e",
        "explanation": "必要な a, f が含まれていない。"
      }
    ],
    "correctChoiceIndex": 2
  },
  {
    "id": 25,
    "body": "メモリインタリーブに関する説明として適切なものはどれか。",
    "choices": [
      {
        "text": "ア: 主記憶と I/O 装置間で CPU を経由せず転送する方式",
        "explanation": "DMA の説明。"
      },
      {
        "text": "イ: キャッシュへの書込み後に主記憶へ書込む方式",
        "explanation": "ライトバックキャッシュの説明。"
      },
      {
        "text": "ウ: 主記憶のデータの一部をキャッシュへコピーする方式",
        "explanation": "キャッシュメモリの説明。"
      },
      {
        "text": "エ: 主記憶を複数バンクに分け並列にアクセスする方式",
        "explanation": "正解。"
      }
    ],
    "correctChoiceIndex": 3
  },
  {
    "id": 26,
    "body": "エッジコンピューティングの説明として最も適切なものはどれか。",
    "choices": [
      {
        "text": "ア: 画面生成をクライアント側で実行し操作性を高めること",
        "explanation": "リッチクライアントの説明。"
      },
      {
        "text": "イ: 必要なときだけサーバを起動する方式",
        "explanation": "サーバレス／FaaS の説明。"
      },
      {
        "text": "ウ: 仮想化で複数サーバを統合し並列処理能力を高めること",
        "explanation": "クラスタリングの説明。"
      },
      {
        "text": "エ: データ源に近い場所で一次処理しリアルタイム性を向上させること",
        "explanation": "正解。"
      }
    ],
    "correctChoiceIndex": 3
  },
  {
    "id": 27,
    "body": "3 次元 CG 処理で“クリッピング”と呼ばれる処理はどれか。",
    "choices": [
      {
        "text": "ア: 最終段階で映像化するレンダリング処理",
        "explanation": "レンダリング。"
      },
      {
        "text": "イ: ウィンドウ外側を除去し内側だけを取り出す処理",
        "explanation": "正解。"
      },
      {
        "text": "ウ: ギザギザを目立たなくするアンチエイリアシング処理",
        "explanation": "誤り。"
      },
      {
        "text": "エ: 物体表面に陰影を付けるシェーディング",
        "explanation": "誤り。"
      }
    ],
    "correctChoiceIndex": 1
  },
  {
    "id": 28,
    "body": "次の関数従属が成立するとき、推移的関数従属として成立するものはどれか。",
    "choices": [
      {
        "text": "ア: 仕入先コード → 仕入担当者コード → 仕入先住所",
        "explanation": "仕入先コード が仕入先住所を直接決定するため推移でない。"
      },
      {
        "text": "イ: 商品コード → 仕入先コード → 商品販売価格",
        "explanation": "末尾が商品販売価格で推移していない。"
      },
      {
        "text": "ウ: 注文コード → 顧客コード → 顧客住所",
        "explanation": "正解。注文コードは顧客住所を推移的に決定する。"
      },
      {
        "text": "エ: 注文コード → 商品コード → 顧客注文数量",
        "explanation": "顧客注文数量は {注文コード, 商品コード} が鍵で推移でない。"
      }
    ],
    "correctChoiceIndex": 2
  },
  {
    "id": 29,
    "body": "トランザクションの ACID 特性のうち、更新処理を完全に行うか全く行わないかを保証する特性はどれか。",
    "choices": [
      {
        "text": "ア: 一貫性 (consistency)",
        "explanation": "整合性を保証する。"
      },
      {
        "text": "イ: 原子性 (atomicity)",
        "explanation": "正解。"
      },
      {
        "text": "ウ: 耐久性 (durability)",
        "explanation": "完了後の永続性。"
      },
      {
        "text": "エ: 独立性 (isolation)",
        "explanation": "分離性。"
      }
    ],
    "correctChoiceIndex": 1
  },
  {
    "id": 30,
    "body": "IPv4 ネットワークで疎通確認に用いられるものはどれか。",
    "choices": [
      {
        "text": "ア: BOOTP",
        "explanation": "自動起動時の IP 付与プロトコル。"
      },
      {
        "text": "イ: DHCP",
        "explanation": "動的 IP アドレス割当。"
      },
      {
        "text": "ウ: MIB",
        "explanation": "SNMP 管理情報ベース。"
      },
      {
        "text": "エ: ping",
        "explanation": "正解。ICMP Echo を送出し応答を確認する。"
      }
    ],
    "correctChoiceIndex": 3
  },
  {
    "id": 31,
    "body": "ドライブバイダウンロード攻撃に該当するものはどれか。",
    "choices": [
      {
        "text": "ア: 盗んだ HDD の中身を公開してダウンロードさせる",
        "explanation": "物理窃取であり DB 級。"
      },
      {
        "text": "イ: メール添付を開かせ PC 内ファイルを暗号化し鍵をダウンロードさせる",
        "explanation": "ランサムウェア型だが drive-by ではない。"
      },
      {
        "text": "ウ: 悪意サイトにアクセスしただけでブラウザ脆弱性を悪用しマルウェア感染させる",
        "explanation": "正解。"
      },
      {
        "text": "エ: 無償ソフトに不正プログラムを同梱しユーザ操作でダウンロードさせる",
        "explanation": "バンドルウェア型。"
      }
    ],
    "correctChoiceIndex": 2
  },
  {
    "id": 32,
    "body": "図のシステム構成で Web アプリの脆弱性対策用 WAF を設置する最適な箇所はどこか。ここで WAF は暗号化／復号機能を持たない。",
    "choices": [
      {
        "text": "ア: インターネットと FW の間 (a)",
        "explanation": "HTTPS のままではペイロードを解析できない。"
      },
      {
        "text": "イ: FW と SSL アクセラレータの間 (b)",
        "explanation": "依然 HTTPS のままで不可。"
      },
      {
        "text": "ウ: SSL アクセラレータと Web サーバの間 (c)",
        "explanation": "正解。SSL アクセラレータで復号され HTTP になるため検査可能。"
      },
      {
        "text": "エ: Web サーバと DB アクセスサービスの間 (d)",
        "explanation": "アプリ内部通信で WAF の目的外。"
      }
    ],
    "correctChoiceIndex": 2
  },
  {
    "id": 33,
    "body": "与えられたフローチャートが ①→②→③→⑤→②→③→④→②→⑥ の順で実行されるようにするには初期値 a, b はどの関係を満たせばよいか（a,b は正整数）。",
    "choices": [
      {
        "text": "ア: a ＝ 2b",
        "explanation": "ループ順序が一致しない。"
      },
      {
        "text": "イ: 2a ＝ b",
        "explanation": "不正解。"
      },
      {
        "text": "ウ: 2a ＝ 3b",
        "explanation": "不正解。"
      },
      {
        "text": "エ: 3a ＝ 2b",
        "explanation": "正解となる流れ（Euclid アルゴリズムのケース）。"
      }
    ],
    "correctChoiceIndex": 3
  },
  {
    "id": 34,
    "body": "スクラム開発で毎日行う短い進捗共有イベントはどれか。",
    "choices": [
      {
        "text": "ア: スプリントプランニング",
        "explanation": "スプリントの計画会議。"
      },
      {
        "text": "イ: スプリントレビュー",
        "explanation": "成果物をレビューする会議。"
      },
      {
        "text": "ウ: デイリースクラム",
        "explanation": "正解。"
      },
      {
        "text": "エ: レトロスペクティブ",
        "explanation": "振り返り会議。"
      }
    ],
    "correctChoiceIndex": 2
  },
  {
    "id": 35,
    "body": "プロジェクトで作業 A が 1 日遅延した。追加費用を最小にするため短縮すべき作業はどれか。",
    "choices": [
      {
        "text": "ア: B",
        "explanation": "費用増加率 6。"
      },
      {
        "text": "イ: C",
        "explanation": "費用増加率 3。"
      },
      {
        "text": "ウ: D",
        "explanation": "費用増加率 2 と最小かつクリティカルパス上。正解。"
      },
      {
        "text": "エ: E",
        "explanation": "費用増加率 2.5。"
      }
    ],
    "correctChoiceIndex": 2
  },
  {
    "id": 36,
    "body": "テレワーキング運用規程の監査で指摘すべき事項はどれか。",
    "choices": [
      {
        "text": "ア: 全従業員が規程を守れば利用可とする",
        "explanation": "規程は妥当。"
      },
      {
        "text": "イ: 使用 PC を会社支給 PC に限定",
        "explanation": "妥当な対策。"
      },
      {
        "text": "ウ: マルウェア対策ソフト導入の要不要を従業員に任せる",
        "explanation": "正解。対策が統制されておらず問題。"
      },
      {
        "text": "エ: 家族に PC を使用させない",
        "explanation": "妥当。"
      }
    ],
    "correctChoiceIndex": 2
  },
  {
    "id": 37,
    "body": "ハイブリッドクラウドを説明したものはどれか。",
    "choices": [
      {
        "text": "ア: クラウド機能を自社用にカスタマイズすること",
        "explanation": "プライベートクラウド導入例。"
      },
      {
        "text": "イ: 消費者向けと法人向けサービスを同時提供するクラウド",
        "explanation": "マルチテナント運用例。"
      },
      {
        "text": "ウ: 有償と無償サービスを併用するクラウド",
        "explanation": "フリーミアムモデル。"
      },
      {
        "text": "エ: プライベートクラウドとパブリッククラウドを連携させる環境",
        "explanation": "正解。"
      }
    ],
    "correctChoiceIndex": 3
  },
  {
    "id": 38,
    "body": "ダイバーシティマネジメントの説明として適切なものはどれか。",
    "choices": [
      {
        "text": "ア: 従業員が仕事と生活の調和を図ること",
        "explanation": "ワークライフバランス。"
      },
      {
        "text": "イ: 性別や年齢，国籍などの多様性を尊重して組織活力を高めること",
        "explanation": "正解。"
      },
      {
        "text": "ウ: 自己設定目標の達成度で評価すること",
        "explanation": "MBO。"
      },
      {
        "text": "エ: 労使協調で収益増大を目指すこと",
        "explanation": "労使協議制。"
      }
    ],
    "correctChoiceIndex": 1
  },
  {
    "id": 39,
    "body": "ERP を説明したものはどれか。",
    "choices": [
      {
        "text": "ア: 営業活動に IT を活用して効率と品質を高める手法",
        "explanation": "SFA。"
      },
      {
        "text": "イ: 小売店支援による取引量拡大手法",
        "explanation": "リテールサポート。"
      },
      {
        "text": "ウ: 企業全体の経営資源を総合的に管理し効率向上を図る手法",
        "explanation": "正解。"
      },
      {
        "text": "エ: 電子的ネットワークで商取引を行う手法",
        "explanation": "EC。"
      }
    ],
    "correctChoiceIndex": 2
  },
  {
    "id": 40,
    "body": "イノベータ理論における“アーリーアダプタ”の説明はどれか。",
    "choices": [
      {
        "text": "ア: 大多数が採用した後で採用する層",
        "explanation": "レイトマジョリティ。"
      },
      {
        "text": "イ: 最も早い段階で受容する層",
        "explanation": "イノベータ。"
      },
      {
        "text": "ウ: 早期に受け入れ流行に敏感で影響力が大きい層",
        "explanation": "正解。"
      },
      {
        "text": "エ: 流行後も採用しない保守的な層",
        "explanation": "ラガード。"
      }
    ],
    "correctChoiceIndex": 2
  },
  {
    "id": 41,
    "body": "CIO (Chief Information Officer) を説明したものはどれか。",
    "choices": [
      {
        "text": "ア: 経営戦略を統括する最高責任者 (CEO)",
        "explanation": "CEO の説明。"
      },
      {
        "text": "イ: 財務面を統括する最高責任者 (CFO)",
        "explanation": "CFO の説明。"
      },
      {
        "text": "ウ: 技術戦略を統括する最高責任者 (CTO)",
        "explanation": "CTO の説明。"
      },
      {
        "text": "エ: 情報システム戦略を統括する最高責任者",
        "explanation": "正解。"
      }
    ],
    "correctChoiceIndex": 3
  },
  {
    "id": 42,
    "body": "ボリュームライセンス契約の説明として最も適切なものはどれか。",
    "choices": [
      {
        "text": "ア: 大量購入者向けにインストール台数を取り決めソフト利用を認める契約",
        "explanation": "正解。"
      },
      {
        "text": "イ: 使用場所を限定し人数無制限とする契約",
        "explanation": "サイトライセンス。"
      },
      {
        "text": "ウ: ダウンロード時に表示される契約内容へ同意し使用を許可する契約",
        "explanation": "クリックラップ契約。"
      },
      {
        "text": "エ: パッケージ開封時に契約が成立するとみなす契約",
        "explanation": "シュリンクラップ契約。"
      }
    ],
    "correctChoiceIndex": 0
  },
  {
    "id": 43,
    "body": "素数列挙関数 findPrimeNumbers の擬似言語に入る a, b の組合せとして正しいものはどれか。",
    "choices": [
      {
        "text": "ア: a: maxNum, b: i ÷ j の余り が 0 と等しい",
        "explanation": "正解。2 から maxNum まで試し割り余りで判定する。"
      },
      {
        "text": "イ: a: maxNum, b: i ÷ j の商 が 1 と等しくない",
        "explanation": "誤り。"
      },
      {
        "text": "ウ: a: maxNum + 1, b: i ÷ j の余り が 0 と等しい",
        "explanation": "ループ上限がずれる。"
      },
      {
        "text": "エ: a: maxNum + 1, b: i ÷ j の商 が 1 と等しくない",
        "explanation": "双方とも不適切。"
      }
    ],
    "correctChoiceIndex": 0
  },
  {
    "id": 44,
    "body": "擬似コード手続 proc2 を実行したときの出力順はどれか。",
    "choices": [
      {
        "text": "ア: “A” “B” “B” “C”",
        "explanation": "proc1 は一度しか呼ばれない。"
      },
      {
        "text": "イ: “A” “C”",
        "explanation": "proc2 の処理を欠いている。"
      },
      {
        "text": "ウ: “A” “C” “B” “C”",
        "explanation": "proc2 の手順と合わない。"
      },
      {
        "text": "エ: “C” “B” “A” “C”",
        "explanation": "正解。proc2→C→B→proc1→A→C の順。"
      }
    ],
    "correctChoiceIndex": 3
  },
  {
    "id": 45,
    "body": "配列 data={2,1,3,5,4} に対し sort(1,5) を呼び出し、最初に /*** α ***/ で出力される内容はどれか。",
    "choices": [
      {
        "text": "ア: 1 2 3 4 5",
        "explanation": "整列後の完全順序ではない。"
      },
      {
        "text": "イ: 1 2 3 5 4",
        "explanation": "誤り。"
      },
      {
        "text": "ウ: 2 1 3 4 5",
        "explanation": "誤り。"
      },
      {
        "text": "エ: 2 1 3 5 4",
        "explanation": "正解。初回 partition で交換なしの状態。"
      }
    ],
    "correctChoiceIndex": 3
  },
  {
    "id": 46,
    "body": "手続 test を実行した直後の hashArray の内容はどれか（初期は {−1×5} ）。",
    "choices": [
      {
        "text": "ア: {−1, 3, −1, 18, 11}",
        "explanation": "インデックス 4 に 3 が先に格納されるため 18 は入らない。"
      },
      {
        "text": "イ: {−1, 11, −1, 3, −1}",
        "explanation": "18 が格納されていない。"
      },
      {
        "text": "ウ: {−1, 11, −1, 18, −1}",
        "explanation": "3 が逆位置。"
      },
      {
        "text": "エ: {−1, 18, −1, 3, 11}",
        "explanation": "正解。"
      }
    ],
    "correctChoiceIndex": 3
  },
  {
    "id": 47,
    "body": "コサイン類似度計算プログラムの空欄 a, b に入る式の組はどれか。",
    "choices": [
      {
        "text": "ア: (vector1[i]×vector2[i])の正の平方根, denominator × (tempの正の平方根)",
        "explanation": "平方根は不要。"
      },
      {
        "text": "イ: (vector1[i]×vector2[i])の正の平方根, denominator ＋ (tempの正の平方根)",
        "explanation": "両方誤り。"
      },
      {
        "text": "ウ: (vector1[i]×vector2[i])の正の平方根, tempの正の平方根",
        "explanation": "分子・分母計算が誤り。"
      },
      {
        "text": "エ: vector1[i]×vector2[i], denominator × (tempの正の平方根)",
        "explanation": "正解。"
      }
    ],
    "correctChoiceIndex": 3
  },
  {
    "id": 48,
    "body": "B 業務委託における複合機設定のリスクとして A 社が対策が必要と判断したものはどれか。",
    "choices": [
      {
        "text": "ア: 攻撃者が複合機を装ったメールを送り従業員がリンクをクリックし個人情報漏えい",
        "explanation": "正解。初期設定のままではメール偽装が容易。"
      },
      {
        "text": "イ: 従業員がスパムと誤認しメールを削除し業務が遅延する",
        "explanation": "リスクは低い。"
      },
      {
        "text": "ウ: 攻撃者が盗聴し PDF を暗号化し身代金を要求",
        "explanation": "添付ファイルは暗号化済みで実現困難。"
      },
      {
        "text": "エ: 攻撃者が盗聴し URL で B サーバにアクセスし個人情報漏えい",
        "explanation": "メール本文に URL であっても認証が必要でリスク低い。"
      }
    ],
    "correctChoiceIndex": 0
  }
]